composio_autogen/__init__.py
composio_autogen/provider.py
composio_autogen/py.typed
composio_autogen-0.10.7.dist-info/METADATA
composio_autogen-0.10.7.dist-info/WHEEL
composio_autogen-0.10.7.dist-info/top_level.txt
composio_autogen-0.10.7.dist-info/RECORD
